grcwa/__init__.py
grcwa/backend.py
grcwa/fft_funs.py
grcwa/kbloch.py
grcwa/primitives.py
grcwa/rcwa.py
tests/__init__.py
tests/test_grcwa.py~
tests/test_kbloch.py
tests/test_kbloch.py~
tests/test_rcwa.py
tests/test_rcwa.py~
tests/utils.py
grcwa-0.1.2.dist-info/AUTHORS.rst
grcwa-0.1.2.dist-info/LICENSE
grcwa-0.1.2.dist-info/METADATA
grcwa-0.1.2.dist-info/WHEEL
grcwa-0.1.2.dist-info/top_level.txt
grcwa-0.1.2.dist-info/RECORD
