Metadata-Version: 2.1
Name: grcwa
Version: 0.1.2
Summary: Rigorous coupled wave analysis supporting automatic differentation with autograd
Home-page: https://github.com/weiliangjinca/grcwa
Author: Weiliang Jin
Author-email: jwlaaa@gmail.com
License: GPL license
Keywords: grcwa
Platform: UNKNOWN
Classifier: License :: OSI Approved :: GNU General Public License v3 (GPLv3)
Classifier: Natural Language :: English
Classifier: Programming Language :: Python :: 3
Classifier: Programming Language :: Python :: 3.5
Classifier: Programming Language :: Python :: 3.6
Classifier: Programming Language :: Python :: 3.7
Classifier: Programming Language :: Python :: 3.8
Requires-Python: >=3.5
Requires-Dist: autograd
Requires-Dist: numpy
